{
  "content": [
    {
      "content": null,
      "created": "2025-10-21T09:23:37.300342Z",
      "format": null,
      "hash": null,
      "hash_algorithm": null,
      "last_modified": "2025-10-21T09:23:34.624488Z",
      "mimetype": null,
      "name": "plot_mlp_training_curves.ipynb",
      "path": "auto_examples/neural_networks/plot_mlp_training_curves.ipynb",
      "size": 6134,
      "type": "notebook",
      "writable": true
    },
    {
      "content": null,
      "created": "2025-10-21T09:23:37.299871Z",
      "format": null,
      "hash": null,
      "hash_algorithm": null,
      "last_modified": "2025-10-21T09:23:34.624314Z",
      "mimetype": null,
      "name": "plot_mlp_alpha.ipynb",
      "path": "auto_examples/neural_networks/plot_mlp_alpha.ipynb",
      "size": 6473,
      "type": "notebook",
      "writable": true
    },
    {
      "content": null,
      "created": "2025-10-21T09:23:37.301013Z",
      "format": null,
      "hash": null,
      "hash_algorithm": null,
      "last_modified": "2025-10-21T09:23:34.624895Z",
      "mimetype": null,
      "name": "plot_rbm_logistic_classification.ipynb",
      "path": "auto_examples/neural_networks/plot_rbm_logistic_classification.ipynb",
      "size": 7662,
      "type": "notebook",
      "writable": true
    },
    {
      "content": null,
      "created": "2025-10-21T09:23:37.300720Z",
      "format": null,
      "hash": null,
      "hash_algorithm": null,
      "last_modified": "2025-10-21T09:23:34.624655Z",
      "mimetype": null,
      "name": "plot_mnist_filters.ipynb",
      "path": "auto_examples/neural_networks/plot_mnist_filters.ipynb",
      "size": 4641,
      "type": "notebook",
      "writable": true
    }
  ],
  "created": "2025-10-21T09:23:37.300879Z",
  "format": "json",
  "hash": null,
  "hash_algorithm": null,
  "last_modified": "2025-10-21T09:23:37.300879Z",
  "mimetype": null,
  "name": "neural_networks",
  "path": "auto_examples/neural_networks",
  "size": null,
  "type": "directory",
  "writable": true
}