{
  "content": [
    {
      "content": null,
      "created": "2025-10-21T09:27:43.427605Z",
      "format": null,
      "hash": null,
      "hash_algorithm": null,
      "last_modified": "2025-10-21T09:27:40.778404Z",
      "mimetype": null,
      "name": "plot_frozen_examples.ipynb",
      "path": "auto_examples/frozen/plot_frozen_examples.ipynb",
      "size": 6818,
      "type": "notebook",
      "writable": true
    }
  ],
  "created": "2025-10-21T09:27:43.427503Z",
  "format": "json",
  "hash": null,
  "hash_algorithm": null,
  "last_modified": "2025-10-21T09:27:43.427503Z",
  "mimetype": null,
  "name": "frozen",
  "path": "auto_examples/frozen",
  "size": null,
  "type": "directory",
  "writable": true
}